Metadata-Version: 2.1
Name: fib142857
Version: 1.0
Summary: To solve fib by recursion
Author: Linus Trovalds
